eurocodedesign/__init__.py
eurocodedesign/eurocodedesign.py
eurocodedesign/core/__init__.py
eurocodedesign/geometry/__init__.py
eurocodedesign/material/__init__.py
eurocodedesign/standard/__init__.py
eurocodedesign/standard/ec0/__init__.py
eurocodedesign/standard/ec1/__init__.py
eurocodedesign/standard/ec3/__init__.py
eurocodedesign/standard/ec8/__init__.py
eurocodedesign/stepper/__init__.py
eurocodedesign-0.0.1.dist-info/AUTHORS.rst
eurocodedesign-0.0.1.dist-info/LICENSE
eurocodedesign-0.0.1.dist-info/METADATA
eurocodedesign-0.0.1.dist-info/WHEEL
eurocodedesign-0.0.1.dist-info/top_level.txt
eurocodedesign-0.0.1.dist-info/RECORD
