Metadata-Version: 2.1
Name: eurocodedesign
Version: 0.0.1
Summary: Typed python framework for eurocode calculations.
Home-page: https://github.com/domthom21/eurocodedesign
Author: Dominik Thomas
Author-email: dominik.thomas@hsu-hh.de
Keywords: eurocodedesign
Classifier: Development Status :: 2 - Pre-Alpha
Classifier: Intended Audience :: Developers
Classifier: Natural Language :: English
Classifier: Programming Language :: Python :: 3.10
Requires-Python: >=3.10
License-File: LICENSE
License-File: AUTHORS.rst
